m26/__init__.py
m26/age.py
m26/age_calculator.py
m26/constants.py
m26/distance.py
m26/elapsed_time.py
m26/run_walk_calculator.py
m26/speed.py
m26-0.3.2.dist-info/METADATA
m26-0.3.2.dist-info/WHEEL
m26-0.3.2.dist-info/licenses/LICENSE
m26-0.3.2.dist-info/RECORD
