Metadata-Version: 2.3
Name: m26
Version: 0.3.2
Summary: m26 - calculations for sports like running, cycling, and swimming
Project-URL: Homepage, https://github.com/cjoakim/m26-py
Project-URL: Issues, https://github.com/cjoakim/m26-py/issues
Project-URL: Repository, https://github.com/cjoakim/m26-py.git
Author-email: Chris Joakim <christopher.joakim@gmail.com>
Maintainer-email: Chris Joakim <christopher.joakim@gmail.com>
License: MIT License
License-File: LICENSE
Keywords: calculator,cycling,pace per mile,running,swimming
Classifier: License :: OSI Approved :: MIT License
Classifier: Operating System :: OS Independent
Classifier: Programming Language :: Python :: 3
Requires-Python: >=3.11
